CHANGES.rst
MANIFEST.in
README.rst
TODO.txt
setup.cfg
setup.py
docs/LICENSE.GPL
docs/LICENSE.txt
redturtle/__init__.py
redturtle.monkey.egg-info/PKG-INFO
redturtle.monkey.egg-info/SOURCES.txt
redturtle.monkey.egg-info/dependency_links.txt
redturtle.monkey.egg-info/entry_points.txt
redturtle.monkey.egg-info/namespace_packages.txt
redturtle.monkey.egg-info/not-zip-safe
redturtle.monkey.egg-info/requires.txt
redturtle.monkey.egg-info/top_level.txt
redturtle/monkey/__init__.py
redturtle/monkey/config.py
redturtle/monkey/configure.zcml
redturtle/monkey/interfaces.py
redturtle/monkey/locator.py
redturtle/monkey/testing.py
redturtle/monkey/vocabularies.py
redturtle/monkey/browser/__init__.py
redturtle/monkey/browser/campaign.py
redturtle/monkey/browser/campaign_created.pt
redturtle/monkey/browser/campaign_wizard.pt
redturtle/monkey/browser/configure.zcml
redturtle/monkey/browser/controlpanel.pt
redturtle/monkey/browser/controlpanel.py
redturtle/monkey/browser/last_campaign.py
redturtle/monkey/browser/newsletter.py
redturtle/monkey/browser/newsletter_subscribed.pt
redturtle/monkey/browser/images/campaign.png
redturtle/monkey/browser/images/monkey.gif
redturtle/monkey/browser/resources/jquery.smartWizard-2.0.min.js
redturtle/monkey/browser/resources/smart_wizard.css
redturtle/monkey/content/__init__.py
redturtle/monkey/content/campaign.py
redturtle/monkey/content/configure.zcml
redturtle/monkey/locales/plone.pot
redturtle/monkey/locales/redturtle.monkey-manual.pot
redturtle/monkey/locales/redturtle.monkey.pot
redturtle/monkey/locales/runI18ndude.sh
redturtle/monkey/locales/it/LC_MESSAGES/plone.po
redturtle/monkey/locales/it/LC_MESSAGES/redturtle.monkey.po
redturtle/monkey/locales/pl/LC_MESSAGES/plone.po
redturtle/monkey/locales/pl/LC_MESSAGES/redturtle.monkey.po
redturtle/monkey/portlet/__init__.py
redturtle/monkey/portlet/addtocampaign.pt
redturtle/monkey/portlet/addtocampaign.py
redturtle/monkey/portlet/configure.zcml
redturtle/monkey/portlet/subscribe.pt
redturtle/monkey/portlet/subscribe.py
redturtle/monkey/portlet/z3cformhelpers.py
redturtle/monkey/profiles/default/actions.xml
redturtle/monkey/profiles/default/browserlayer.xml
redturtle/monkey/profiles/default/controlpanel.xml
redturtle/monkey/profiles/default/cssregistry.xml
redturtle/monkey/profiles/default/jsregistry.xml
