Metadata-Version: 1.0
Name: redturtle.monkey
Version: 1.2.1
Summary: mailchimp integration for Plone.
Home-page: http://plone.org/products/redturtle.monkey
Author: Andrew Mleczko
Author-email: sviluppoplone@redturtle.it
License: GPL
Platform: UNKNOWN
Classifier: Framework :: Plone
Classifier: Framework :: Plone :: 4.0
Classifier: Framework :: Plone :: 4.1
Classifier: Framework :: Plone :: 4.2
Classifier: Framework :: Plone :: 4.3
Classifier: Programming Language :: Python
